LICENSE.txt
MANIFEST.in
README.md
pyproject.toml
setup.py
scikit_sparse.egg-info/PKG-INFO
scikit_sparse.egg-info/SOURCES.txt
scikit_sparse.egg-info/dependency_links.txt
scikit_sparse.egg-info/requires.txt
scikit_sparse.egg-info/top_level.txt
sksparse/__init__.py
sksparse/cholmod.pyx
sksparse/cholmod_backward_compatible.h
sksparse/test_cholmod.py
sksparse/test_data/illc1033.mtx.gz
sksparse/test_data/illc1033_rhs1.mtx.gz
sksparse/test_data/illc1850.mtx.gz
sksparse/test_data/illc1850_rhs1.mtx.gz
sksparse/test_data/well1033.mtx.gz
sksparse/test_data/well1033_rhs1.mtx.gz
sksparse/test_data/well1850.mtx.gz
sksparse/test_data/well1850_rhs1.mtx.gz
tests/test_cholmod.py