Metadata-Version: 2.1
Name: scikit-sparse
Version: 0.4.11
Summary: Scikit sparse matrix package
Home-page: https://github.com/scikit-sparse/scikit-sparse
Maintainer: Justin Ellis
Maintainer-email: justin.ellis18@gmail.com
License: BSD
Classifier: Development Status :: 3 - Alpha
Classifier: Environment :: Console
Classifier: Intended Audience :: Developers
Classifier: Intended Audience :: Science/Research
Classifier: License :: OSI Approved :: BSD License
Classifier: Programming Language :: Cython
Classifier: Topic :: Scientific/Engineering
Classifier: Topic :: Scientific/Engineering :: Mathematics
Classifier: Programming Language :: Python :: 3
Classifier: Programming Language :: Python :: 3.6
Classifier: Programming Language :: Python :: 3.7
Classifier: Programming Language :: Python :: 3.8
Classifier: Programming Language :: Python :: 3.9
Classifier: Programming Language :: Python :: 3.10
Classifier: Programming Language :: Python :: 3.11
Requires-Python: >=3.6, <3.12
License-File: LICENSE.txt
